materialist/__init__.py
materialist/client.py
materialist/quantum_espresso.py
materialist-0.0.2.dist-info/METADATA
materialist-0.0.2.dist-info/WHEEL
materialist-0.0.2.dist-info/RECORD
